CHANGELOG.txt
LICENCE.txt
MANIFEST.in
README.txt
setup.py
zmqpubsub/__init__.py
zmqpubsub/zmq_publisher.py
zmqpubsub/zmq_subscriber.py
zmqpubsub.egg-info/PKG-INFO
zmqpubsub.egg-info/SOURCES.txt
zmqpubsub.egg-info/dependency_links.txt
zmqpubsub.egg-info/requires.txt
zmqpubsub.egg-info/top_level.txt