Metadata-Version: 1.1
Name: zmqpubsub
Version: 0.0.1
Summary: Python package to create publishers & subscribers to send JSON payloads over ZMQ.
Home-page: UNKNOWN
Author: Vincent Charpentier
Author-email: vincent.charpentier@imec.be
License: MIT
Keywords: zmq,publisher,subscriber
Platform: UNKNOWN
Classifier: Intended Audience :: Developers
Classifier: Operating System :: POSIX :: Linux
Classifier: Operating System :: MacOS
Classifier: License :: OSI Approved :: MIT License
Classifier: Programming Language :: Python :: 3
